[
  {
    "ContainingType": "Mos3ef.Api.Controllers.AccountController",
    "Method": "AssignRole",
    "RelativePath": "api/Account/assign-role",
    "HttpMethod": "POST",
    "IsController": true,
    "Order": 0,
    "Parameters": [
      {
        "Name": "dto",
        "Type": "Mos3ef.BLL.Dtos.Auth.AssignRoleDto",
        "IsRequired": true
      }
    ],
    "ReturnTypes": []
  },
  {
    "ContainingType": "Mos3ef.Api.Controllers.AccountController",
    "Method": "ChangePassword",
    "RelativePath": "api/Account/change-password",
    "HttpMethod": "POST",
    "IsController": true,
    "Order": 0,
    "Parameters": [
      {
        "Name": "dto",
        "Type": "Mos3ef.BLL.Dtos.Auth.ChangePasswordDto",
        "IsRequired": true
      }
    ],
    "ReturnTypes": []
  },
  {
    "ContainingType": "Mos3ef.Api.Controllers.AccountController",
    "Method": "CreateRole",
    "RelativePath": "api/Account/create-role",
    "HttpMethod": "POST",
    "IsController": true,
    "Order": 0,
    "Parameters": [
      {
        "Name": "roleName",
        "Type": "System.String",
        "IsRequired": true
      }
    ],
    "ReturnTypes": []
  },
  {
    "ContainingType": "Mos3ef.Api.Controllers.AccountController",
    "Method": "CreateUser",
    "RelativePath": "api/Account/create-user",
    "HttpMethod": "POST",
    "IsController": true,
    "Order": 0,
    "Parameters": [
      {
        "Name": "dto",
        "Type": "Mos3ef.BLL.Dtos.Auth.CreateUserDto",
        "IsRequired": true
      }
    ],
    "ReturnTypes": []
  },
  {
    "ContainingType": "Mos3ef.Api.Controllers.AccountController",
    "Method": "Login",
    "RelativePath": "api/Account/login",
    "HttpMethod": "POST",
    "IsController": true,
    "Order": 0,
    "Parameters": [
      {
        "Name": "dto",
        "Type": "Mos3ef.BLL.Dtos.Auth.LoginDto",
        "IsRequired": true
      }
    ],
    "ReturnTypes": []
  },
  {
    "ContainingType": "Mos3ef.Api.Controllers.AccountController",
    "Method": "RegisterHospital",
    "RelativePath": "api/Account/register/hospital",
    "HttpMethod": "POST",
    "IsController": true,
    "Order": 0,
    "Parameters": [
      {
        "Name": "dto",
        "Type": "Mos3ef.BLL.Dtos.Auth.HospitalRegisterDto",
        "IsRequired": true
      }
    ],
    "ReturnTypes": []
  },
  {
    "ContainingType": "Mos3ef.Api.Controllers.AccountController",
    "Method": "RegisterPatient",
    "RelativePath": "api/Account/register/patient",
    "HttpMethod": "POST",
    "IsController": true,
    "Order": 0,
    "Parameters": [
      {
        "Name": "dto",
        "Type": "Mos3ef.BLL.Dtos.Auth.PatientRegisterDto",
        "IsRequired": true
      }
    ],
    "ReturnTypes": []
  },
  {
    "ContainingType": "Mos3ef.Api.Controllers.AccountController",
    "Method": "UpdateUser",
    "RelativePath": "api/Account/update-user",
    "HttpMethod": "PUT",
    "IsController": true,
    "Order": 0,
    "Parameters": [
      {
        "Name": "dto",
        "Type": "Mos3ef.BLL.Dtos.Auth.UpdateUserDto",
        "IsRequired": true
      }
    ],
    "ReturnTypes": []
  },
  {
    "ContainingType": "Mos3ef.Api.Controllers.HospitalController",
    "Method": "AddAsync",
    "RelativePath": "api/Hospital/Add",
    "HttpMethod": "POST",
    "IsController": true,
    "Order": 0,
    "Parameters": [
      {
        "Name": "hospitalAddDto",
        "Type": "Mos3ef.BLL.Dtos.Hospital.HospitalAddDto",
        "IsRequired": true
      }
    ],
    "ReturnTypes": []
  },
  {
    "ContainingType": "Mos3ef.Api.Controllers.HospitalController",
    "Method": "AddServiceAsync",
    "RelativePath": "api/Hospital/AddService",
    "HttpMethod": "POST",
    "IsController": true,
    "Order": 0,
    "Parameters": [
      {
        "Name": "servicesAddDto",
        "Type": "Mos3ef.BLL.Dtos.Services.ServicesAddDto",
        "IsRequired": true
      }
    ],
    "ReturnTypes": []
  },
  {
    "ContainingType": "Mos3ef.Api.Controllers.HospitalController",
    "Method": "DeleteAsync",
    "RelativePath": "api/Hospital/Delete/{id}",
    "HttpMethod": "DELETE",
    "IsController": true,
    "Order": 0,
    "Parameters": [
      {
        "Name": "id",
        "Type": "System.Int32",
        "IsRequired": true
      }
    ],
    "ReturnTypes": []
  },
  {
    "ContainingType": "Mos3ef.Api.Controllers.HospitalController",
    "Method": "DeleteServiceAsync",
    "RelativePath": "api/Hospital/DeleteService/{id}",
    "HttpMethod": "DELETE",
    "IsController": true,
    "Order": 0,
    "Parameters": [
      {
        "Name": "id",
        "Type": "System.Int32",
        "IsRequired": true
      }
    ],
    "ReturnTypes": []
  },
  {
    "ContainingType": "Mos3ef.Api.Controllers.HospitalController",
    "Method": "GetAsync",
    "RelativePath": "api/Hospital/Get/{id}",
    "HttpMethod": "GET",
    "IsController": true,
    "Order": 0,
    "Parameters": [
      {
        "Name": "id",
        "Type": "System.Int32",
        "IsRequired": true
      }
    ],
    "ReturnTypes": []
  },
  {
    "ContainingType": "Mos3ef.Api.Controllers.HospitalController",
    "Method": "GetAll",
    "RelativePath": "api/Hospital/GetAll",
    "HttpMethod": "GET",
    "IsController": true,
    "Order": 0,
    "Parameters": [],
    "ReturnTypes": []
  },
  {
    "ContainingType": "Mos3ef.Api.Controllers.HospitalController",
    "Method": "GetDashboardStatsAsync",
    "RelativePath": "api/Hospital/GetDashboardStats/{id}",
    "HttpMethod": "GET",
    "IsController": true,
    "Order": 0,
    "Parameters": [
      {
        "Name": "id",
        "Type": "System.Int32",
        "IsRequired": true
      }
    ],
    "ReturnTypes": []
  },
  {
    "ContainingType": "Mos3ef.Api.Controllers.HospitalController",
    "Method": "GetServicesReviewsAsync",
    "RelativePath": "api/Hospital/GetServicesReviews/{id}",
    "HttpMethod": "GET",
    "IsController": true,
    "Order": 0,
    "Parameters": [
      {
        "Name": "id",
        "Type": "System.Int32",
        "IsRequired": true
      }
    ],
    "ReturnTypes": []
  },
  {
    "ContainingType": "Mos3ef.Api.Controllers.HospitalController",
    "Method": "UpdateAsync",
    "RelativePath": "api/Hospital/Update/{id}",
    "HttpMethod": "PUT",
    "IsController": true,
    "Order": 0,
    "Parameters": [
      {
        "Name": "id",
        "Type": "System.Int32",
        "IsRequired": true
      },
      {
        "Name": "hospitalUpdateDto",
        "Type": "Mos3ef.BLL.Dtos.Hospital.HospitalUpdateDto",
        "IsRequired": true
      }
    ],
    "ReturnTypes": []
  },
  {
    "ContainingType": "Mos3ef.Api.Controllers.HospitalController",
    "Method": "UpdateServiceAsync",
    "RelativePath": "api/Hospital/UpdateService/{id}",
    "HttpMethod": "PUT",
    "IsController": true,
    "Order": 0,
    "Parameters": [
      {
        "Name": "id",
        "Type": "System.Int32",
        "IsRequired": true
      },
      {
        "Name": "servicesUpdateDto",
        "Type": "Mos3ef.BLL.Dtos.Services.ServicesUpdateDto",
        "IsRequired": true
      }
    ],
    "ReturnTypes": []
  },
  {
    "ContainingType": "Mos3ef.Api.Controllers.PatientsController",
    "Method": "GetPatientById",
    "RelativePath": "api/Patients/{id}",
    "HttpMethod": "GET",
    "IsController": true,
    "Order": 0,
    "Parameters": [
      {
        "Name": "id",
        "Type": "System.Int32",
        "IsRequired": true
      }
    ],
    "ReturnTypes": []
  },
  {
    "ContainingType": "Mos3ef.Api.Controllers.PatientsController",
    "Method": "GetMyProfile",
    "RelativePath": "api/Patients/GetMyProfile",
    "HttpMethod": "GET",
    "IsController": true,
    "Order": 0,
    "Parameters": [],
    "ReturnTypes": [
      {
        "Type": "Mos3ef.BLL.Dtos.Patient.PatientReadDto",
        "MediaTypes": [
          "text/plain",
          "application/json",
          "text/json"
        ],
        "StatusCode": 200
      }
    ]
  },
  {
    "ContainingType": "Mos3ef.Api.Controllers.PatientsController",
    "Method": "GetMySavedServices",
    "RelativePath": "api/Patients/GetMySavedServices",
    "HttpMethod": "GET",
    "IsController": true,
    "Order": 0,
    "Parameters": [
      {
        "Name": "pageNumber",
        "Type": "System.Int32",
        "IsRequired": false
      },
      {
        "Name": "pageSize",
        "Type": "System.Int32",
        "IsRequired": false
      }
    ],
    "ReturnTypes": [
      {
        "Type": "Mos3ef.BLL.Dtos.Common.PagedResult\u00601[[Mos3ef.BLL.Dtos.Services.ServiceReadDto, Mos3ef.BLL, Version=1.0.0.0, Culture=neutral, PublicKeyToken=null]]",
        "MediaTypes": [
          "text/plain",
          "application/json",
          "text/json"
        ],
        "StatusCode": 200
      }
    ]
  },
  {
    "ContainingType": "Mos3ef.Api.Controllers.PatientsController",
    "Method": "RemoveServiceFromMyList",
    "RelativePath": "api/Patients/my-saved-services/{serviceId}",
    "HttpMethod": "DELETE",
    "IsController": true,
    "Order": 0,
    "Parameters": [
      {
        "Name": "serviceId",
        "Type": "System.Int32",
        "IsRequired": true
      }
    ],
    "ReturnTypes": []
  },
  {
    "ContainingType": "Mos3ef.Api.Controllers.PatientsController",
    "Method": "SaveServiceToMyList",
    "RelativePath": "api/Patients/SaveServiceToMyList/{serviceId}",
    "HttpMethod": "POST",
    "IsController": true,
    "Order": 0,
    "Parameters": [
      {
        "Name": "serviceId",
        "Type": "System.Int32",
        "IsRequired": true
      }
    ],
    "ReturnTypes": []
  },
  {
    "ContainingType": "Mos3ef.Api.Controllers.PatientsController",
    "Method": "UpdateMyProfile",
    "RelativePath": "api/Patients/UpdateMyProfile",
    "HttpMethod": "PUT",
    "IsController": true,
    "Order": 0,
    "Parameters": [
      {
        "Name": "patientUpdateDto",
        "Type": "Mos3ef.BLL.Dtos.Patient.PatientUpdateDto",
        "IsRequired": true
      }
    ],
    "ReturnTypes": []
  },
  {
    "ContainingType": "Mos3ef.Api.Controllers.ReviewController",
    "Method": "AddReview",
    "RelativePath": "api/Review",
    "HttpMethod": "POST",
    "IsController": true,
    "Order": 0,
    "Parameters": [
      {
        "Name": "review",
        "Type": "Mos3ef.BLL.Dtos.Review.ReviewAddDto",
        "IsRequired": true
      }
    ],
    "ReturnTypes": []
  },
  {
    "ContainingType": "Mos3ef.Api.Controllers.ReviewController",
    "Method": "Update",
    "RelativePath": "api/Review",
    "HttpMethod": "PUT",
    "IsController": true,
    "Order": 0,
    "Parameters": [
      {
        "Name": "Id",
        "Type": "System.Int32",
        "IsRequired": false
      },
      {
        "Name": "review",
        "Type": "Mos3ef.BLL.Dtos.Review.ReviewUpdateDto",
        "IsRequired": true
      }
    ],
    "ReturnTypes": []
  },
  {
    "ContainingType": "Mos3ef.Api.Controllers.ReviewController",
    "Method": "Delete",
    "RelativePath": "api/Review/{Id}",
    "HttpMethod": "DELETE",
    "IsController": true,
    "Order": 0,
    "Parameters": [
      {
        "Name": "Id",
        "Type": "System.Int32",
        "IsRequired": true
      }
    ],
    "ReturnTypes": []
  },
  {
    "ContainingType": "Mos3ef.Api.Controllers.ReviewController",
    "Method": "GetReviewsByService",
    "RelativePath": "api/Review/{serviceId}",
    "HttpMethod": "GET",
    "IsController": true,
    "Order": 0,
    "Parameters": [
      {
        "Name": "serviceId",
        "Type": "System.Int32",
        "IsRequired": true
      }
    ],
    "ReturnTypes": []
  },
  {
    "ContainingType": "Mos3ef.Api.Controllers.ServicesController",
    "Method": "GetAllServices",
    "RelativePath": "api/Services",
    "HttpMethod": "GET",
    "IsController": true,
    "Order": 0,
    "Parameters": [
      {
        "Name": "onlyAvailable",
        "Type": "System.Boolean",
        "IsRequired": false
      },
      {
        "Name": "pageNumber",
        "Type": "System.Int32",
        "IsRequired": false
      },
      {
        "Name": "pageSize",
        "Type": "System.Int32",
        "IsRequired": false
      }
    ],
    "ReturnTypes": []
  },
  {
    "ContainingType": "Mos3ef.Api.Controllers.ServicesController",
    "Method": "GetServiceById",
    "RelativePath": "api/Services/{id}",
    "HttpMethod": "GET",
    "IsController": true,
    "Order": 0,
    "Parameters": [
      {
        "Name": "id",
        "Type": "System.Int32",
        "IsRequired": true
      }
    ],
    "ReturnTypes": []
  },
  {
    "ContainingType": "Mos3ef.Api.Controllers.ServicesController",
    "Method": "GetServiceHospital",
    "RelativePath": "api/Services/{id}/hospital",
    "HttpMethod": "GET",
    "IsController": true,
    "Order": 0,
    "Parameters": [
      {
        "Name": "id",
        "Type": "System.Int32",
        "IsRequired": true
      }
    ],
    "ReturnTypes": []
  },
  {
    "ContainingType": "Mos3ef.Api.Controllers.ServicesController",
    "Method": "GetServiceReviews",
    "RelativePath": "api/Services/{id}/reviews",
    "HttpMethod": "GET",
    "IsController": true,
    "Order": 0,
    "Parameters": [
      {
        "Name": "id",
        "Type": "System.Int32",
        "IsRequired": true
      }
    ],
    "ReturnTypes": []
  },
  {
    "ContainingType": "Mos3ef.Api.Controllers.ServicesController",
    "Method": "CompareServices",
    "RelativePath": "api/Services/compare",
    "HttpMethod": "POST",
    "IsController": true,
    "Order": 0,
    "Parameters": [
      {
        "Name": "compareDto",
        "Type": "Mos3ef.BLL.Dtos.Compare.CompareRequestDto",
        "IsRequired": true
      }
    ],
    "ReturnTypes": []
  },
  {
    "ContainingType": "Mos3ef.Api.Controllers.ServicesController",
    "Method": "FilterServices",
    "RelativePath": "api/Services/filter",
    "HttpMethod": "GET",
    "IsController": true,
    "Order": 0,
    "Parameters": [
      {
        "Name": "HasEmergency",
        "Type": "System.Nullable\u00601[[System.Boolean, System.Private.CoreLib, Version=8.0.0.0, Culture=neutral, PublicKeyToken=7cec85d7bea7798e]]",
        "IsRequired": false
      },
      {
        "Name": "HasIcu",
        "Type": "System.Nullable\u00601[[System.Boolean, System.Private.CoreLib, Version=8.0.0.0, Culture=neutral, PublicKeyToken=7cec85d7bea7798e]]",
        "IsRequired": false
      },
      {
        "Name": "HasNicu",
        "Type": "System.Nullable\u00601[[System.Boolean, System.Private.CoreLib, Version=8.0.0.0, Culture=neutral, PublicKeyToken=7cec85d7bea7798e]]",
        "IsRequired": false
      },
      {
        "Name": "HospitalName",
        "Type": "System.String",
        "IsRequired": false
      },
      {
        "Name": "MaxPrice",
        "Type": "System.Nullable\u00601[[System.Decimal, System.Private.CoreLib, Version=8.0.0.0, Culture=neutral, PublicKeyToken=7cec85d7bea7798e]]",
        "IsRequired": false
      },
      {
        "Name": "MinRating",
        "Type": "System.Nullable\u00601[[System.Int32, System.Private.CoreLib, Version=8.0.0.0, Culture=neutral, PublicKeyToken=7cec85d7bea7798e]]",
        "IsRequired": false
      },
      {
        "Name": "Region",
        "Type": "System.String",
        "IsRequired": false
      },
      {
        "Name": "OnlyAvailable",
        "Type": "System.Boolean",
        "IsRequired": false
      },
      {
        "Name": "Keyword",
        "Type": "System.String",
        "IsRequired": false
      },
      {
        "Name": "SortBy",
        "Type": "System.String",
        "IsRequired": false
      },
      {
        "Name": "IsAscending",
        "Type": "System.Boolean",
        "IsRequired": false
      },
      {
        "Name": "UserLatitude",
        "Type": "System.Nullable\u00601[[System.Double, System.Private.CoreLib, Version=8.0.0.0, Culture=neutral, PublicKeyToken=7cec85d7bea7798e]]",
        "IsRequired": false
      },
      {
        "Name": "UserLongitude",
        "Type": "System.Nullable\u00601[[System.Double, System.Private.CoreLib, Version=8.0.0.0, Culture=neutral, PublicKeyToken=7cec85d7bea7798e]]",
        "IsRequired": false
      },
      {
        "Name": "RadiusKm",
        "Type": "System.Nullable\u00601[[System.Double, System.Private.CoreLib, Version=8.0.0.0, Culture=neutral, PublicKeyToken=7cec85d7bea7798e]]",
        "IsRequired": false
      },
      {
        "Name": "PageNumber",
        "Type": "System.Int32",
        "IsRequired": false
      },
      {
        "Name": "PageSize",
        "Type": "System.Int32",
        "IsRequired": false
      }
    ],
    "ReturnTypes": []
  },
  {
    "ContainingType": "Mos3ef.Api.Controllers.ServicesController",
    "Method": "SearchServices",
    "RelativePath": "api/Services/search",
    "HttpMethod": "GET",
    "IsController": true,
    "Order": 0,
    "Parameters": [
      {
        "Name": "keyword",
        "Type": "System.String",
        "IsRequired": false
      },
      {
        "Name": "lat",
        "Type": "System.Nullable\u00601[[System.Double, System.Private.CoreLib, Version=8.0.0.0, Culture=neutral, PublicKeyToken=7cec85d7bea7798e]]",
        "IsRequired": false
      },
      {
        "Name": "lng",
        "Type": "System.Nullable\u00601[[System.Double, System.Private.CoreLib, Version=8.0.0.0, Culture=neutral, PublicKeyToken=7cec85d7bea7798e]]",
        "IsRequired": false
      },
      {
        "Name": "radiusKm",
        "Type": "System.Nullable\u00601[[System.Double, System.Private.CoreLib, Version=8.0.0.0, Culture=neutral, PublicKeyToken=7cec85d7bea7798e]]",
        "IsRequired": false
      },
      {
        "Name": "onlyAvailable",
        "Type": "System.Boolean",
        "IsRequired": false
      },
      {
        "Name": "pageNumber",
        "Type": "System.Int32",
        "IsRequired": false
      },
      {
        "Name": "pageSize",
        "Type": "System.Int32",
        "IsRequired": false
      }
    ],
    "ReturnTypes": []
  }
]